{"audio_filepath": "audio_samples/M_0234_9y9m_1.wav", "offset": 0.74, "duration": 1.27, "label": "UNK", "uniq_id": "M_0234_9y9m_1"}
{"audio_filepath": "audio_samples/M_0234_9y9m_1.wav", "offset": 2.48, "duration": 2.87, "label": "UNK", "uniq_id": "M_0234_9y9m_1"}
{"audio_filepath": "audio_samples/M_0234_9y9m_1.wav", "offset": 5.62, "duration": 2.05, "label": "UNK", "uniq_id": "M_0234_9y9m_1"}
{"audio_filepath": "audio_samples/M_0234_9y9m_1.wav", "offset": 8.0, "duration": 0.93, "label": "UNK", "uniq_id": "M_0234_9y9m_1"}
{"audio_filepath": "audio_samples/M_0234_9y9m_1.wav", "offset": 9.48, "duration": 1.91, "label": "UNK", "uniq_id": "M_0234_9y9m_1"}
{"audio_filepath": "audio_samples/M_0234_9y9m_1.wav", "offset": 12.96, "duration": 2.03, "label": "UNK", "uniq_id": "M_0234_9y9m_1"}
{"audio_filepath": "audio_samples/M_0234_9y9m_1.wav", "offset": 16.1, "duration": 1.91, "label": "UNK", "uniq_id": "M_0234_9y9m_1"}
{"audio_filepath": "audio_samples/M_0234_9y9m_1.wav", "offset": 18.18, "duration": 1.29, "label": "UNK", "uniq_id": "M_0234_9y9m_1"}
{"audio_filepath": "audio_samples/M_0234_9y9m_1.wav", "offset": 21.18, "duration": 3.37, "label": "UNK", "uniq_id": "M_0234_9y9m_1"}
{"audio_filepath": "audio_samples/M_0234_9y9m_1.wav", "offset": 24.72, "duration": 0.99, "label": "UNK", "uniq_id": "M_0234_9y9m_1"}
{"audio_filepath": "audio_samples/M_0234_9y9m_1.wav", "offset": 26.4, "duration": 1.21, "label": "UNK", "uniq_id": "M_0234_9y9m_1"}
{"audio_filepath": "audio_samples/M_0234_9y9m_1.wav", "offset": 28.94, "duration": 1.49, "label": "UNK", "uniq_id": "M_0234_9y9m_1"}
{"audio_filepath": "audio_samples/M_0234_9y9m_1.wav", "offset": 30.66, "duration": 2.11, "label": "UNK", "uniq_id": "M_0234_9y9m_1"}
{"audio_filepath": "audio_samples/M_0234_9y9m_1.wav", "offset": 33.4, "duration": 1.09, "label": "UNK", "uniq_id": "M_0234_9y9m_1"}
{"audio_filepath": "audio_samples/M_0234_9y9m_1.wav", "offset": 34.98, "duration": 0.37, "label": "UNK", "uniq_id": "M_0234_9y9m_1"}
{"audio_filepath": "audio_samples/M_0234_9y9m_1.wav", "offset": 36.04, "duration": 2.65, "label": "UNK", "uniq_id": "M_0234_9y9m_1"}
{"audio_filepath": "audio_samples/M_0234_9y9m_1.wav", "offset": 39.8, "duration": 1.37, "label": "UNK", "uniq_id": "M_0234_9y9m_1"}
{"audio_filepath": "audio_samples/M_0234_9y9m_1.wav", "offset": 41.44, "duration": 1.71, "label": "UNK", "uniq_id": "M_0234_9y9m_1"}
{"audio_filepath": "audio_samples/M_0234_9y9m_1.wav", "offset": 43.94, "duration": 3.91, "label": "UNK", "uniq_id": "M_0234_9y9m_1"}
{"audio_filepath": "audio_samples/M_0234_9y9m_1.wav", "offset": 48.08, "duration": 1.01, "label": "UNK", "uniq_id": "M_0234_9y9m_1"}
{"audio_filepath": "audio_samples/M_0234_9y9m_1.wav", "offset": 49.86, "duration": 0.85, "label": "UNK", "uniq_id": "M_0234_9y9m_1"}
{"audio_filepath": "audio_samples/M_0234_9y9m_1.wav", "offset": 51.92, "duration": 1.53, "label": "UNK", "uniq_id": "M_0234_9y9m_1"}
{"audio_filepath": "audio_samples/M_0234_9y9m_1.wav", "offset": 53.86, "duration": 0.31, "label": "UNK", "uniq_id": "M_0234_9y9m_1"}
{"audio_filepath": "audio_samples/M_0234_9y9m_1.wav", "offset": 54.44, "duration": 1.45, "label": "UNK", "uniq_id": "M_0234_9y9m_1"}
{"audio_filepath": "audio_samples/M_0234_9y9m_1.wav", "offset": 56.32, "duration": 0.97, "label": "UNK", "uniq_id": "M_0234_9y9m_1"}
{"audio_filepath": "audio_samples/M_0234_9y9m_1.wav", "offset": 57.44, "duration": 1.79, "label": "UNK", "uniq_id": "M_0234_9y9m_1"}
{"audio_filepath": "audio_samples/M_0234_9y9m_1.wav", "offset": 59.46, "duration": 1.23, "label": "UNK", "uniq_id": "M_0234_9y9m_1"}
{"audio_filepath": "audio_samples/M_0234_9y9m_1.wav", "offset": 60.84, "duration": 1.27, "label": "UNK", "uniq_id": "M_0234_9y9m_1"}
{"audio_filepath": "audio_samples/M_0234_9y9m_1.wav", "offset": 62.8, "duration": 0.67, "label": "UNK", "uniq_id": "M_0234_9y9m_1"}
{"audio_filepath": "audio_samples/M_0234_9y9m_1.wav", "offset": 64.76, "duration": 1.07, "label": "UNK", "uniq_id": "M_0234_9y9m_1"}
{"audio_filepath": "audio_samples/M_0234_9y9m_1.wav", "offset": 66.62, "duration": 1.50999, "label": "UNK", "uniq_id": "M_0234_9y9m_1"}
{"audio_filepath": "audio_samples/M_0234_9y9m_1.wav", "offset": 68.68, "duration": 2.45, "label": "UNK", "uniq_id": "M_0234_9y9m_1"}
{"audio_filepath": "audio_samples/M_0234_9y9m_1.wav", "offset": 71.42, "duration": 1.21, "label": "UNK", "uniq_id": "M_0234_9y9m_1"}
{"audio_filepath": "audio_samples/M_0234_9y9m_1.wav", "offset": 73.0, "duration": 0.85, "label": "UNK", "uniq_id": "M_0234_9y9m_1"}
{"audio_filepath": "audio_samples/M_0234_9y9m_1.wav", "offset": 74.22, "duration": 3.13, "label": "UNK", "uniq_id": "M_0234_9y9m_1"}
{"audio_filepath": "audio_samples/M_0234_9y9m_1.wav", "offset": 77.6, "duration": 3.81001, "label": "UNK", "uniq_id": "M_0234_9y9m_1"}
{"audio_filepath": "audio_samples/M_0234_9y9m_1.wav", "offset": 82.06, "duration": 1.37, "label": "UNK", "uniq_id": "M_0234_9y9m_1"}
{"audio_filepath": "audio_samples/M_0234_9y9m_1.wav", "offset": 83.58, "duration": 0.89, "label": "UNK", "uniq_id": "M_0234_9y9m_1"}
{"audio_filepath": "audio_samples/M_0234_9y9m_1.wav", "offset": 84.98, "duration": 0.93, "label": "UNK", "uniq_id": "M_0234_9y9m_1"}
{"audio_filepath": "audio_samples/M_0234_9y9m_1.wav", "offset": 86.06, "duration": 0.87, "label": "UNK", "uniq_id": "M_0234_9y9m_1"}
{"audio_filepath": "audio_samples/M_0234_9y9m_1.wav", "offset": 87.16, "duration": 0.67, "label": "UNK", "uniq_id": "M_0234_9y9m_1"}
{"audio_filepath": "audio_samples/M_0234_9y9m_1.wav", "offset": 88.06, "duration": 1.11, "label": "UNK", "uniq_id": "M_0234_9y9m_1"}
{"audio_filepath": "audio_samples/M_0234_9y9m_1.wav", "offset": 91.0, "duration": 4.45, "label": "UNK", "uniq_id": "M_0234_9y9m_1"}
{"audio_filepath": "audio_samples/M_0234_9y9m_1.wav", "offset": 95.8, "duration": 2.21, "label": "UNK", "uniq_id": "M_0234_9y9m_1"}
{"audio_filepath": "audio_samples/M_0234_9y9m_1.wav", "offset": 98.22, "duration": 1.07, "label": "UNK", "uniq_id": "M_0234_9y9m_1"}
{"audio_filepath": "audio_samples/M_0234_9y9m_1.wav", "offset": 100.06, "duration": 3.09, "label": "UNK", "uniq_id": "M_0234_9y9m_1"}
{"audio_filepath": "audio_samples/M_0234_9y9m_1.wav", "offset": 103.4, "duration": 2.31, "label": "UNK", "uniq_id": "M_0234_9y9m_1"}
{"audio_filepath": "audio_samples/M_0234_9y9m_1.wav", "offset": 106.96, "duration": 4.29, "label": "UNK", "uniq_id": "M_0234_9y9m_1"}
{"audio_filepath": "audio_samples/M_0234_9y9m_1.wav", "offset": 111.48, "duration": 2.35, "label": "UNK", "uniq_id": "M_0234_9y9m_1"}
{"audio_filepath": "audio_samples/M_0234_9y9m_1.wav", "offset": 114.1, "duration": 1.31001, "label": "UNK", "uniq_id": "M_0234_9y9m_1"}
{"audio_filepath": "audio_samples/M_0234_9y9m_1.wav", "offset": 115.68, "duration": 1.11, "label": "UNK", "uniq_id": "M_0234_9y9m_1"}
{"audio_filepath": "audio_samples/M_0234_9y9m_1.wav", "offset": 117.22, "duration": 4.01, "label": "UNK", "uniq_id": "M_0234_9y9m_1"}
{"audio_filepath": "audio_samples/M_0234_9y9m_1.wav", "offset": 121.4, "duration": 0.83, "label": "UNK", "uniq_id": "M_0234_9y9m_1"}
{"audio_filepath": "audio_samples/M_0234_9y9m_1.wav", "offset": 122.68, "duration": 2.09, "label": "UNK", "uniq_id": "M_0234_9y9m_1"}
{"audio_filepath": "audio_samples/M_0234_9y9m_1.wav", "offset": 125.22, "duration": 0.55, "label": "UNK", "uniq_id": "M_0234_9y9m_1"}
{"audio_filepath": "audio_samples/M_0234_9y9m_1.wav", "offset": 126.76, "duration": 1.87, "label": "UNK", "uniq_id": "M_0234_9y9m_1"}
{"audio_filepath": "audio_samples/M_0234_9y9m_1.wav", "offset": 129.0, "duration": 1.27, "label": "UNK", "uniq_id": "M_0234_9y9m_1"}
{"audio_filepath": "audio_samples/M_0234_9y9m_1.wav", "offset": 130.52, "duration": 1.50999, "label": "UNK", "uniq_id": "M_0234_9y9m_1"}
{"audio_filepath": "audio_samples/M_0234_9y9m_1.wav", "offset": 132.36, "duration": 1.14999, "label": "UNK", "uniq_id": "M_0234_9y9m_1"}
{"audio_filepath": "audio_samples/M_0234_9y9m_1.wav", "offset": 134.24001, "duration": 3.26999, "label": "UNK", "uniq_id": "M_0234_9y9m_1"}
{"audio_filepath": "audio_samples/M_0234_9y9m_1.wav", "offset": 137.78, "duration": 0.55, "label": "UNK", "uniq_id": "M_0234_9y9m_1"}
{"audio_filepath": "audio_samples/M_0234_9y9m_1.wav", "offset": 138.94, "duration": 0.69, "label": "UNK", "uniq_id": "M_0234_9y9m_1"}
{"audio_filepath": "audio_samples/M_0234_9y9m_1.wav", "offset": 140.58, "duration": 3.13, "label": "UNK", "uniq_id": "M_0234_9y9m_1"}
{"audio_filepath": "audio_samples/M_0234_9y9m_1.wav", "offset": 144.08, "duration": 0.53, "label": "UNK", "uniq_id": "M_0234_9y9m_1"}
{"audio_filepath": "audio_samples/M_0234_9y9m_1.wav", "offset": 144.8, "duration": 0.42999, "label": "UNK", "uniq_id": "M_0234_9y9m_1"}
{"audio_filepath": "audio_samples/M_0234_9y9m_1.wav", "offset": 145.52, "duration": 2.34999, "label": "UNK", "uniq_id": "M_0234_9y9m_1"}
{"audio_filepath": "audio_samples/M_0234_9y9m_1.wav", "offset": 148.02, "duration": 1.64999, "label": "UNK", "uniq_id": "M_0234_9y9m_1"}
{"audio_filepath": "audio_samples/M_0234_9y9m_1.wav", "offset": 151.2, "duration": 3.67, "label": "UNK", "uniq_id": "M_0234_9y9m_1"}
{"audio_filepath": "audio_samples/M_0234_9y9m_1.wav", "offset": 156.84, "duration": 0.89, "label": "UNK", "uniq_id": "M_0234_9y9m_1"}
{"audio_filepath": "audio_samples/M_0234_9y9m_1.wav", "offset": 158.0, "duration": 1.14999, "label": "UNK", "uniq_id": "M_0234_9y9m_1"}
{"audio_filepath": "audio_samples/M_0234_9y9m_1.wav", "offset": 159.56, "duration": 0.71001, "label": "UNK", "uniq_id": "M_0234_9y9m_1"}
{"audio_filepath": "audio_samples/M_0234_9y9m_1.wav", "offset": 161.2, "duration": 0.71001, "label": "UNK", "uniq_id": "M_0234_9y9m_1"}
{"audio_filepath": "audio_samples/M_0234_9y9m_1.wav", "offset": 162.32001, "duration": 2.82999, "label": "UNK", "uniq_id": "M_0234_9y9m_1"}
{"audio_filepath": "audio_samples/M_0234_9y9m_1.wav", "offset": 165.72, "duration": 0.45, "label": "UNK", "uniq_id": "M_0234_9y9m_1"}
{"audio_filepath": "audio_samples/M_0234_9y9m_1.wav", "offset": 166.60001, "duration": 0.89, "label": "UNK", "uniq_id": "M_0234_9y9m_1"}
{"audio_filepath": "audio_samples/M_0234_9y9m_1.wav", "offset": 168.60001, "duration": 0.75, "label": "UNK", "uniq_id": "M_0234_9y9m_1"}
{"audio_filepath": "audio_samples/M_0234_9y9m_1.wav", "offset": 169.64, "duration": 0.45, "label": "UNK", "uniq_id": "M_0234_9y9m_1"}
{"audio_filepath": "audio_samples/M_0234_9y9m_1.wav", "offset": 170.46001, "duration": 0.39, "label": "UNK", "uniq_id": "M_0234_9y9m_1"}
{"audio_filepath": "audio_samples/M_0234_9y9m_1.wav", "offset": 171.28, "duration": 3.63, "label": "UNK", "uniq_id": "M_0234_9y9m_1"}
{"audio_filepath": "audio_samples/M_0234_9y9m_1.wav", "offset": 176.10001, "duration": 2.12999, "label": "UNK", "uniq_id": "M_0234_9y9m_1"}
{"audio_filepath": "audio_samples/M_0234_9y9m_1.wav", "offset": 178.67999, "duration": 0.79001, "label": "UNK", "uniq_id": "M_0234_9y9m_1"}
{"audio_filepath": "audio_samples/M_0234_9y9m_1.wav", "offset": 179.7, "duration": 0.77, "label": "UNK", "uniq_id": "M_0234_9y9m_1"}
{"audio_filepath": "audio_samples/M_0234_9y9m_1.wav", "offset": 181.0, "duration": 0.27, "label": "UNK", "uniq_id": "M_0234_9y9m_1"}
{"audio_filepath": "audio_samples/M_0234_9y9m_1.wav", "offset": 182.12, "duration": 1.57001, "label": "UNK", "uniq_id": "M_0234_9y9m_1"}
{"audio_filepath": "audio_samples/M_0234_9y9m_1.wav", "offset": 184.94, "duration": 2.09673, "label": "UNK", "uniq_id": "M_0234_9y9m_1"}
